LICENSE
MANIFEST.in
README.rst
setup.py
mustaine/__init__.py
mustaine/_util.py
mustaine/client.py
mustaine/encoder.py
mustaine/parser.py
mustaine/protocol.py
mustaine.egg-info/PKG-INFO
mustaine.egg-info/SOURCES.txt
mustaine.egg-info/dependency_links.txt
mustaine.egg-info/top_level.txt
mustaine.egg-info/zip-safe