Metadata-Version: 1.0
Name: mustaine
Version: 0.1.7
Summary: Hessian RPC Library
Home-page: http://github.com/bgilmore/mustaine
Author: Brandon Gilmore
Author-email: brandon@mg2.org
License: BSD
Platform: any
Classifier: Development Status :: 4 - Beta
Classifier: Intended Audience :: Developers
Classifier: License :: OSI Approved :: BSD License
Classifier: Operating System :: OS Independent
Classifier: Programming Language :: Python
Classifier: Topic :: Software Development :: Object Brokering
Classifier: Topic :: Software Development :: Libraries
